adafruit_circuitpython_esp32spi-11.1.0.dist-info/licenses/LICENSE
adafruit_esp32spi/PWMOut.py
adafruit_esp32spi/__init__.py
adafruit_esp32spi/adafruit_esp32spi.py
adafruit_esp32spi/adafruit_esp32spi_socketpool.py
adafruit_esp32spi/adafruit_esp32spi_wifimanager.py
adafruit_esp32spi/digitalio.py
adafruit_esp32spi/socketpool.py
adafruit_esp32spi/wifimanager.py
adafruit_circuitpython_esp32spi-11.1.0.dist-info/METADATA
adafruit_circuitpython_esp32spi-11.1.0.dist-info/WHEEL
adafruit_circuitpython_esp32spi-11.1.0.dist-info/top_level.txt
adafruit_circuitpython_esp32spi-11.1.0.dist-info/RECORD
