Metadata-Version: 2.4
Name: adafruit-circuitpython-esp32spi
Version: 11.1.0
Summary: CircuitPython driver library for using ESP32 as WiFi  co-processor using SPI
Author-email: Adafruit Industries <circuitpython@adafruit.com>
License: MIT
Project-URL: Homepage, https://github.com/adafruit/Adafruit_CircuitPython_ESP32SPI
Keywords: adafruit,blinka,circuitpython,micropython,esp32spi,wifi,esp32
Classifier: Intended Audience :: Developers
Classifier: Topic :: Software Development :: Libraries
Classifier: Topic :: Software Development :: Embedded Systems
Classifier: Topic :: System :: Hardware
Classifier: License :: OSI Approved :: MIT License
Classifier: Programming Language :: Python :: 3
License-File: LICENSE
Requires-Dist: Adafruit-Blinka
Requires-Dist: adafruit-circuitpython-busdevice
Requires-Dist: adafruit-circuitpython-connectionmanager
Requires-Dist: adafruit-circuitpython-requests
Provides-Extra: optional
Requires-Dist: adafruit-circuitpython-neopixel; extra == "optional"
Requires-Dist: adafruit-circuitpython-fancyled; extra == "optional"
Requires-Dist: adafruit-circuitpython-requests; extra == "optional"
Dynamic: license-file
